Metadata-Version: 2.1
Name: odoo12-addon-hr-attendance-report-theoretical-time
Version: 12.0.1.5.1
Summary: Theoretical vs Attended Time Analysis
Home-page: https://github.com/OCA/hr
Author: Tecnativa, Odoo Community Association (OCA)
Author-email: support@odoo-community.org
License: AGPL-3
Platform: UNKNOWN
Classifier: Programming Language :: Python
Classifier: Framework :: Odoo
Classifier: License :: OSI Approved :: GNU Affero General Public License v3
Requires-Python: >=3.5
Requires-Dist: odoo12-addon-hr-holidays-public
Requires-Dist: odoo (<12.1dev,>=12.0a)
